[
    {
        "function": "minecraft:copy_nbt",
        "source": {
            "type": "minecraft:storage",
            "source": "eoflib:config"
        },
        "ops": [
            {
                "source": "tlc.Abilities[].SilkWings[].tertiary[].mc_data",
                "target": "{}",
                "op": "merge"
            },
            {
                "source": "tlc.Abilities[].SilkWings[].tertiary[].eof_data",
                "target": "eof_data",
                "op": "replace"
            }
        ]
    }
]
